{"name":"build-javascript","namedChunkGroups":{"polyfill":{"name":"polyfill","assets":[{"name":"webpack-runtime-3b8d8a1f0fda2141d8bb.js","size":4994},{"name":"polyfill-4718f0fec20e0d09d7f5.js","size":85862}],"filteredAssets":0,"assetsSize":90856,"filteredAuxiliaryAssets":2,"auxiliaryAssetsSize":228030},"app":{"name":"app","assets":[{"name":"webpack-runtime-3b8d8a1f0fda2141d8bb.js","size":4994},{"name":"framework-6bdc9aaa9caa3de6408b.js","size":129775},{"name":"app-6e6cd8c9baa1e1b3751e.js","size":99278}],"filteredAssets":0,"assetsSize":234047,"filteredAuxiliaryAssets":3,"auxiliaryAssetsSize":798416},"component---src-pages-404-tsx":{"name":"component---src-pages-404-tsx","assets":[{"name":"commons-bfa499289dbc118f868f.js","size":7626},{"name":"component---src-pages-404-tsx-0a9aaedfa0ff89c4ceec.js","size":1133}],"filteredAssets":0,"assetsSize":8759,"filteredAuxiliaryAssets":2,"auxiliaryAssetsSize":18761},"component---src-pages-index-tsx":{"name":"component---src-pages-index-tsx","assets":[{"name":"styles.9ab12b773ebf72405934.css","size":19013},{"name":"commons-bfa499289dbc118f868f.js","size":7626},{"name":"component---src-pages-index-tsx-0ac923e58bf493995383.js","size":108575}],"filteredAssets":0,"assetsSize":135214,"filteredAuxiliaryAssets":9,"auxiliaryAssetsSize":526557}},"assetsByChunkName":{"polyfill":["webpack-runtime-3b8d8a1f0fda2141d8bb.js","polyfill-4718f0fec20e0d09d7f5.js"],"app":["webpack-runtime-3b8d8a1f0fda2141d8bb.js","framework-6bdc9aaa9caa3de6408b.js","app-6e6cd8c9baa1e1b3751e.js"],"component---src-pages-404-tsx":["commons-bfa499289dbc118f868f.js","component---src-pages-404-tsx-0a9aaedfa0ff89c4ceec.js"],"component---src-pages-index-tsx":["styles.9ab12b773ebf72405934.css","commons-bfa499289dbc118f868f.js","component---src-pages-index-tsx-0ac923e58bf493995383.js"]},"childAssetsByChunkName":{}}